kk777/m1.py
kk777-0.1.dist-info/METADATA
kk777-0.1.dist-info/WHEEL
kk777-0.1.dist-info/top_level.txt
kk777-0.1.dist-info/RECORD
