Metadata-Version: 2.1
Name: kk777
Version: 0.1
Summary: thane batch sat 2019
Home-page: UNKNOWN
Author: Kamal Kumar
Author-email: kamalsir@ymail.com
License: UNKNOWN
Platform: UNKNOWN
